kcc_example_package/__init__.py
kcc_example_package/kcc_example.py
test/__init__.py
test/test_kcc_example.py
kcc_example_package-0.1.2.dist-info/LICENSE
kcc_example_package-0.1.2.dist-info/METADATA
kcc_example_package-0.1.2.dist-info/WHEEL
kcc_example_package-0.1.2.dist-info/top_level.txt
kcc_example_package-0.1.2.dist-info/RECORD
