Metadata-Version: 2.1
Name: kcc-example-package
Version: 0.1.2
Summary: Example to test setting up a pip package.
Home-page: https://github.com/kcc3/kcc-example-package
Author: Kevin Chang
Author-email: kevin.chaohwa.chang@gmail.com
License: LICENSE
Platform: UNKNOWN
Classifier: License :: OSI Approved :: MIT License
Classifier: Programming Language :: Python :: 2
Classifier: Programming Language :: Python :: 2.7
